abstra/__init__.py
abstra/ai.py
abstra/cli.py
abstra/common.py
abstra/compat.py
abstra/connectors.py
abstra/ensurepath.py
abstra/files.py
abstra/forms.py
abstra/hooks.py
abstra/logging.py
abstra/messages.py
abstra/tables.py
abstra/tasks.py
abstra/types.py
abstra/workflows.py
abstra/connectors/__init__.py
abstra_internals/__init__.py
abstra_internals/constants.py
abstra_internals/constants_test.py
abstra_internals/contracts_generated.py
abstra_internals/credentials.py
abstra_internals/credentials_test.py
abstra_internals/debug.py
abstra_internals/email_signer.py
abstra_internals/env_masker.py
abstra_internals/env_masker_test.py
abstra_internals/environment.py
abstra_internals/execution.py
abstra_internals/logger.py
abstra_internals/logs_watcher.py
abstra_internals/modules.py
abstra_internals/modules_test.py
abstra_internals/proxy.py
abstra_internals/proxy_test.py
abstra_internals/settings.py
abstra_internals/settings_test.py
abstra_internals/signals.py
abstra_internals/stdio_patcher.py
abstra_internals/tasks_watcher.py
abstra_internals/tasks_watcher_test.py
abstra_internals/threaded.py
abstra_internals/usage.py
abstra_internals/version.py
abstra_internals/cloud/__init__.py
abstra_internals/cloud/metrics_reporter.py
abstra_internals/cloud/server.py
abstra_internals/cloud/server_application.py
abstra_internals/cloud/server_hooks.py
abstra_internals/cloud/web_editor_worker.py
abstra_internals/cloud/worker.py
abstra_internals/cloud_api/__init__.py
abstra_internals/cloud_api/http_client.py
abstra_internals/consts/__init__.py
abstra_internals/consts/filepaths.py
abstra_internals/controllers/__init__.py
abstra_internals/controllers/ai.py
abstra_internals/controllers/auth.py
abstra_internals/controllers/codebase.py
abstra_internals/controllers/codebase_events.py
abstra_internals/controllers/docs.py
abstra_internals/controllers/env_vars.py
abstra_internals/controllers/git.py
abstra_internals/controllers/main.py
abstra_internals/controllers/pysa.py
abstra-3.26.7.dist-info/METADATA
abstra-3.26.7.dist-info/WHEEL
abstra-3.26.7.dist-info/entry_points.txt
abstra-3.26.7.dist-info/top_level.txt
abstra-3.26.7.dist-info/RECORD
