Metadata-Version: 2.4
Name: abstra
Version: 3.26.7
Summary: Abstra Lib
Home-page: https://github.com/abstra-app/abstra-lib
License: MIT
Requires-Python: >=3.9, <4
Requires-Dist: colorama>=0.4.6
Requires-Dist: colour>=0.1.5
Requires-Dist: fire>=0.5.0
Requires-Dist: Flask>=2.2.2
Requires-Dist: Flask-Cors>=4.0.0
Requires-Dist: flask-sock>=0.6.0
Requires-Dist: jedi>=0.19.0
Requires-Dist: multipart>=0.2.4
Requires-Dist: progress>=1.6
Requires-Dist: pyjwt[crypto]>=2.8.0
Requires-Dist: requests>=2.31.0
Requires-Dist: websockets>=15.0.1
Requires-Dist: simplejson>=3.19.1
Requires-Dist: validators>=0.20.0
Requires-Dist: Werkzeug>=2.2.3
Requires-Dist: setuptools
Requires-Dist: importlib_metadata
Requires-Dist: debugpy
Requires-Dist: python-dotenv>=1.0.0
Requires-Dist: unidecode>=1.3.7
Requires-Dist: pydantic>=2.6.4
Requires-Dist: packaging
Requires-Dist: sentry_sdk[flask]>=2.19.1
Requires-Dist: jsonpath-ng>=1.6.1
Requires-Dist: gunicorn==23.0.0
Requires-Dist: gevent>=24.2.1
Requires-Dist: userpath
Requires-Dist: Pillow
Requires-Dist: pika==1.3.2
Requires-Dist: puremagic==1.28
Requires-Dist: psutil
Requires-Dist: pypdfium2==4.30.0
Requires-Dist: watchdog==4.0.2
Requires-Dist: mail-parser==4.1.2
Requires-Dist: certifi
Requires-Dist: abstra-json-sql>=0.0.12
Requires-Dist: ty
Dynamic: description
Dynamic: description-content-type
Dynamic: home-page
Dynamic: license
Dynamic: requires-dist
Dynamic: requires-python
Dynamic: summary
